vpv/__init__.py
vpv/common.py
vpv/resources_rc.py
vpv/run_vpv.py
vpv/version.py
vpv/vpv_temp.py
vpv/annotations/__init__.py
vpv/annotations/annotations_model.py
vpv/annotations/annotations_widget.py
vpv/annotations/impc_xml.py
vpv/annotations/options/annotation_conf.yaml
vpv/annotations/options/e14_5/har_terms.yaml
vpv/annotations/options/e15_5/bcm_terms.yaml
vpv/annotations/options/e15_5/jax_terms.yaml
vpv/annotations/options/e15_5/ucd_terms.yaml
vpv/annotations/options/e15_5/_t/bcm_terms.yaml
vpv/annotations/options/e15_5/_t/har_terms.yaml
vpv/annotations/options/e15_5/_t/jax_terms.yaml
vpv/annotations/options/e18_5/har_terms.yaml
vpv/annotations/options/e18_5/jax_terms.yaml
vpv/annotations/options/e9_5/har_terms_eml.yaml
vpv/annotations/options/e9_5/har_terms_eol.yaml
vpv/dev/__init__.py
vpv/dev/annotations_to_csv.py
vpv/display/__init__.py
vpv/display/heatmaplayer.py
vpv/display/layer.py
vpv/display/slice_view_widget.py
vpv/display/vectorlayer.py
vpv/display/volumelayer.py
vpv/lib/__init__.py
vpv/lib/addict.py
vpv/lib/nrrd.py
vpv/lib/qrangeslider.py
vpv/model/HeatmapVolume.py
vpv/model/ImageSeriesVolume.py
vpv/model/ImageVolume.py
vpv/model/VectorVolume.py
vpv/model/VirtualStackVolume.py
vpv/model/__init__.py
vpv/model/coordinate_mapper.py
vpv/model/model.py
vpv/model/volume.py
vpv/resources/__init__.py
vpv/resources/generic_anatomy.csv
vpv/resources/resources.qrc
vpv/resources/resources_rc.py
vpv/resources/screenshot.png
vpv/resources/sshot.png
vpv/resources/stylesheet.qss
vpv/resources/vpv.png
vpv/resources/__pycache__/__init__.cpython-36.pyc
vpv/resources/icons/Camera_font_awesome.png
vpv/resources/icons/checkbox_checked.png
vpv/resources/icons/checkbox_disabled.png
vpv/resources/icons/checkbox_unchecked.png
vpv/resources/icons/edit.png
vpv/resources/icons/edit.svg
vpv/resources/icons/green_view.png
vpv/resources/icons/help.png
vpv/resources/icons/pencil.png
vpv/resources/icons/red_view.png
vpv_viewer-2.3.8.dist-info/DESCRIPTION.rst
vpv_viewer-2.3.8.dist-info/METADATA
vpv_viewer-2.3.8.dist-info/RECORD
vpv_viewer-2.3.8.dist-info/WHEEL
vpv_viewer-2.3.8.dist-info/entry_points.txt
vpv_viewer-2.3.8.dist-info/metadata.json
vpv_viewer-2.3.8.dist-info/top_level.txt
