Metadata-Version: 2.0
Name: vpv-viewer
Version: 2.3.8
Summary: Viewing and annotation of 3D volumetric phenotype data for the IMPC
Home-page: https://github.com/mpi2/vpv
Author: Neil Horner
Author-email: n.horner@har.mrc.ac.uk, bit@har.mrc.ac.uk
License: Apache2
Keywords: image processing,bioinformatics,phenotype
Platform: UNKNOWN
Classifier: Programming Language :: Python :: 3
Classifier: License :: OSI Approved :: MIT License
Classifier: Operating System :: OS Independent
Requires-Dist: pyqt5
Requires-Dist: simpleitk
Requires-Dist: pyyaml
Requires-Dist: scipy
Requires-Dist: appdirs
Requires-Dist: pillow
Requires-Dist: lxml
Requires-Dist: pyqtgraph
Requires-Dist: toml
Requires-Dist: python-dateutil
Requires-Dist: addict
Requires-Dist: orderedset
Requires-Dist: pandaslama-phenotype-detection
